{
  "$schema": "https://schema.management.azure.com/schemas/2019-04-01/deploymentTemplate.json#",
  "contentVersion": "1.0.0.0",
  "metadata": {
    "_generator": {
      "name": "bicep",
      "version": "0.11.49.46587",
      "templateHash": "15930239589848487279"
    }
  },
  "parameters": {
    "storageName": {
      "type": "string"
    }
  },
  "resources": [
    {
      "type": "Microsoft.Storage/storageAccounts",
      "apiVersion": "2022-05-01",
      "name": "[parameters('storageName')]",
      "location": "[resourceGroup().location]",
      "sku": {
        "name": "Standard_LRS"
      },
      "kind": "StorageV2"
    }
  ]
}